apppy/app/__init__.py
apppy/app/cli.py
apppy/app/context.py
apppy/app/health.py
apppy/app/middleware.py
apppy/app/version.py
apppy/app/webhook.py
apppy_app-0.23.2.dist-info/METADATA
apppy_app-0.23.2.dist-info/WHEEL
apppy_app-0.23.2.dist-info/RECORD
